dunia/__init__.py
dunia/aio.py
dunia/browser.py
dunia/document.py
dunia/element.py
dunia/error.py
dunia/extraction.py
dunia/helpers.py
dunia/html.py
dunia/login.py
dunia/lexbor/__init__.py
dunia/lexbor/_core.py
dunia/lexbor/page.py
dunia/log/__init__.py
dunia/log/_core.py
dunia/lxml/__init__.py
dunia/lxml/_core.py
dunia/lxml/page.py
dunia/modest/__init__.py
dunia/modest/_core.py
dunia/modest/page.py
dunia/playwright/__init__.py
dunia/playwright/_types.py
dunia/playwright/browser.py
dunia-0.1.5.dist-info/METADATA
dunia-0.1.5.dist-info/WHEEL
dunia-0.1.5.dist-info/licenses/LICENSE
dunia-0.1.5.dist-info/RECORD
