Metadata-Version: 2.4
Name: dunia
Version: 0.1.5
Summary: HTML parsing of JavaScript heavy websites using multiple backends (lxml, modest, playwright, etc.).
Author-email: Danyal Zia Khan <danyalziakhan@gmail.com>
License-Expression: MIT
License-File: LICENSE
Classifier: Development Status :: 5 - Production/Stable
Classifier: Environment :: Other Environment
Classifier: Intended Audience :: Developers
Classifier: License :: OSI Approved :: MIT License
Classifier: Operating System :: OS Independent
Classifier: Programming Language :: Python :: 3
Classifier: Programming Language :: Python :: 3.10
Classifier: Programming Language :: Python :: 3.11
Classifier: Programming Language :: Python :: 3.12
Classifier: Programming Language :: Python :: 3.13
Classifier: Programming Language :: Python :: Implementation :: CPython
Classifier: Topic :: Software Development :: Libraries :: Python Modules
Requires-Python: <3.14,>=3.10
Requires-Dist: async-lru<3,>=2.0.4
Requires-Dist: async-timeout<5,>=4.0.3
Requires-Dist: backoff<3,>=2.2.1
Requires-Dist: charset-normalizer<4,>=3.3.2
Requires-Dist: cssselect<2,>=1.2.0
Requires-Dist: loguru<0.8,>=0.7.2
Requires-Dist: lxml<6,>=5.2.2
Requires-Dist: playwright<2,>=1.44.0
Requires-Dist: selectolax<0.4,>=0.3.21
Requires-Dist: throttler<2,>=1.2.2
